yootils/__init__.py
yootils/py.typed
yootils/dagster/__init__.py
yootils/dagster/automation_conditions.py
yootils/datetime/__init__.py
yootils/datetime/utcdatetime.py
yootils/datetime/utcnow.py
yootils/functools/__init__.py
yootils/functools/propagate_error.py
yootils/google/__init__.py
yootils/google/auth/__init__.py
yootils/google/auth/get_service_account_oidc_jwt.py
yootils/google/bigquery/__init__.py
yootils/google/bigquery/convert_pydantic_model_to_schema.py
yootils/google/gmail/__init__.py
yootils/google/gmail/send_email.py
yootils/jsonschema/__init__.py
yootils/jsonschema/pydantic_utils.py
yootils/langchain/__init__.py
yootils/langchain/chat_models.py
yootils/time/__init__.py
yootils/time/time_execution.py
yootils-0.2.6.dist-info/licenses/LICENSE
yootils-0.2.6.dist-info/METADATA
yootils-0.2.6.dist-info/WHEEL
yootils-0.2.6.dist-info/top_level.txt
yootils-0.2.6.dist-info/RECORD
