Metadata-Version: 2.4
Name: yootils
Version: 0.2.6
Summary: Stuff I often need.
Author-email: Duy Nguyen <hello.duyknguyen@gmail.com>
License: Copyright 2024 Duy Nguyen
Project-URL: homepage, https://github.com/duynguyen158/yootils
Project-URL: repository, https://github.com/duynguyen158/yootils
Requires-Python: >=3.11
License-File: LICENSE
Provides-Extra: dagster
Requires-Dist: dagster>=1.10.0; extra == "dagster"
Provides-Extra: google
Requires-Dist: aiohttp>=3.10.5; extra == "google"
Requires-Dist: annotated-types>=0.7.0; extra == "google"
Requires-Dist: asyncer>=0.0.8; extra == "google"
Requires-Dist: google-api-python-client>=2.169.0; extra == "google"
Requires-Dist: google-auth>=2.34.0; extra == "google"
Requires-Dist: google-cloud-bigquery>=3.33.0; extra == "google"
Requires-Dist: urllib3>=2.2.2; extra == "google"
Requires-Dist: pydantic>=2.11.4; extra == "google"
Requires-Dist: requests>=2.32.3; extra == "google"
Provides-Extra: jsonschema
Requires-Dist: anyio>=4.9.0; extra == "jsonschema"
Requires-Dist: asyncer>=0.0.8; extra == "jsonschema"
Requires-Dist: datamodel-code-generator>=0.30.1; extra == "jsonschema"
Requires-Dist: pydantic>=2.11.4; extra == "jsonschema"
Provides-Extra: langchain
Requires-Dist: langchain>=0.3.25; extra == "langchain"
Requires-Dist: langchain-community>=0.3.25; extra == "langchain"
Requires-Dist: langchain-core>=0.3.65; extra == "langchain"
Requires-Dist: pydantic>=2.11.4; extra == "langchain"
Dynamic: license-file
